[
  {
    "variation": "default",
    "version": "sktwi1xtmkfgx8626",
    "items": [
      {
        "question": "tool",
        "answer": [
          {
            "type": "paragraph",
            "text": "Minim ullamco consectetur laboris consequat nisi commodo laborum aute dolor consectetur pariatur adipisicing consequat velit. Aute incididunt reprehenderit quis. Consequat ut reprehenderit eu excepteur.",
            "spans": []
          }
        ]
      }
    ],
    "primary": {
      "title": [
        {
          "type": "heading2",
          "text": "Equipment",
          "spans": []
        }
      ]
    },
    "slice_type": "faq"
  }
]